ExportCsvToInflux/__init__.py
ExportCsvToInflux/__version__.py
ExportCsvToInflux/base_object.py
ExportCsvToInflux/command_object.py
ExportCsvToInflux/config_object.py
ExportCsvToInflux/csv_object.py
ExportCsvToInflux/exporter_object.py
ExportCsvToInflux/influx_object.py
ExportCsvToInflux-0.2.2.dist-info/LICENSE
ExportCsvToInflux-0.2.2.dist-info/METADATA
ExportCsvToInflux-0.2.2.dist-info/WHEEL
ExportCsvToInflux-0.2.2.dist-info/entry_points.txt
ExportCsvToInflux-0.2.2.dist-info/top_level.txt
ExportCsvToInflux-0.2.2.dist-info/RECORD
