Metadata-Version: 2.1
Name: ExportCsvToInflux
Version: 0.2.2
Summary: Export
Home-page: https://github.com/Bugazelle/export-csv-to-influx
Author: Bugazelle
Author-email: 463407426@qq.com
License: bsd-3-clause-clear
Download-URL: https://github.com/Bugazelle/export-csv-to-influx/archive/v0.2.2.tar.gz
Keywords: python,csv,influx
Platform: UNKNOWN
Classifier: Development Status :: 5 - Production/Stable
Classifier: Intended Audience :: Developers
Classifier: Natural Language :: English
Classifier: Programming Language :: Python
Classifier: Programming Language :: Python :: 2.7
Classifier: Programming Language :: Python :: 3.4
Classifier: Programming Language :: Python :: 3.5
Classifier: Programming Language :: Python :: 3.6
Classifier: Programming Language :: Python :: 3.7
Classifier: Programming Language :: Python :: 3.8
Classifier: Programming Language :: Python :: 3.9
Classifier: Programming Language :: Python :: 3.9
License-File: LICENSE
Requires-Dist: influxdb (>=5.3.1)
Requires-Dist: influxdb-client[ciso] (>=1.25.0)
Requires-Dist: python-dateutil (>=2.8.0)
Requires-Dist: chardet (>=4.0.0)
